{
  "regions":{
    "Drajkmyr Marsh Region":"Swampy",
    "AG_InfernalRegion":"Earthlike",
    "Red Mountain Region":"Reddish",
    "Brodir Grove Region":"Earthlike",
    "Shipal-Shin Region":"Ashen",
    "Nedothril Region":"Ashen",
    "aa22_Region_Massama":"Earthlike",
    "Sea of Ghosts Region":"Ashen",
    "Falkheim Region":"Earthlike",
    "Mephalan Vales Region":"Ashen",
    "Alt Orethan Region":"Ashen",
    "Arnesian Jungle Region":"Swampy",
    "Grazelands Region":"Ashen",
    "Shambalun Veil Region":"Ashen",
    "Skaldring Mountains Region":"Earthlike",
    "Gold Coast Region":"Earthlike",
    "Roth Roryn Region":"Ashen",
    "Boethiah's Spine Region":"Ashen",
    "Druadach Highlands Region":"Earthlike",
    "Isinfier Plains Region":"Earthlike",
    "Valstaag Highlands Region":"Earthlike",
    "Bitter Coast Region":"Swampy",
    "Azura's Coast Region":"Ashen",
    "Sheogorad":"Ashen",
    "Clockwork City":"Earthlike",
    "DD_Region":"Earthlike",
    "AG_AngryWizardRegion":"Earthlike",
    "Armun Ashlands Region":"Reddish",
    "Ashlands Region":"Reddish",
    "Old Ebonheart Region":"Ashen",
    "Hirstaang Forest Region":"Earthlike",
    "Padomaic Ocean Region":"Ashen",
    "Throat of the World Region":"Earthlike",
    "Julan-Shar Region":"Ashen",
    "Othreleth Woods Region":"Ashen",
    "Somewhere Else":"Earthlike",
    "Kreathi Vale Region":"Earthlike",
    "White Plains Region":"Earthlike",
    "Grey Meadows Region":"Swampy",
    "Gilded Hills Region":"Earthlike",
    "Sacred Lands Region":"Ashen",
    "Thirsk Region":"Earthlike",
    "Telvanni Isles Region":"Ashen",
    "Colovian Highlands Region":"Earthlike",
    "Molagreahd Region":"Ashen",
    "Thirr Valley Region":"Ashen",
    "Crescent Moon Isle Region":"Earthlike",
    "Rift Valley Region":"Earthlike",
    "Clambering Moor Region":"Ashen",
    "Lan Orethan Region":"Ashen",
    "Jerall Mountains Region":"Earthlike",
    "Colovian Barrowlands Region":"Earthlike",
    "Deshaan Plains Region":"Swampy",
    "Sundered Scar Region":"Swampy",
    "Northshore Region":"Earthlike",
    "Dagon Urul Region":"Ashen",
    "AG_ZealRegion":"Earthlike",
    "Vivec Cantons Region":"Ashen",
    "Hrimbald Plateau Region":"Earthlike",
    "Moesring Mountains Region":"Earthlike",
    "Broken Cape Region":"Earthlike",
    "Stirk Isle Region":"Earthlike",
    "Ysheim Region":"Earthlike",
    "ds22_InnerSea":"Earthlike",
    "Seitur Region":"Ashen",
    "POT Azura's Coast Region":"Earthlike",
    "Salt Marsh Region":"Swampy",
    "West Weald Region":"Earthlike",
    "Molag Mar Region":"Reddish",
    "Mhorkren Hills Region":"Earthlike",
    "Lorchwuir Heath Region":"Earthlike",
    "Firemoth Region":"CC_Firemoth",
    "West Gash Region":"Ashen",
    "Helnim Fields Region":"Ashen",
    "Gorvigh Mountains Region":"Earthlike",
    "Hirsing Forest Region":"Earthlike",
    "Felsaad Coast Region":"Earthlike",
    "Abecean Sea Region":"Earthlike",
    "Kilkreath Mountains Region":"Earthlike",
    "Molag Ruhn Region":"Ashen",
    "Wuurthal Dale Region":"Earthlike",
    "SHP Sea of Ghosts Region":"Earthlike",
    "Kvetchi Pass Region":"Earthlike",
    "Uncharted Sea of Ghosts Region":"Earthlike",
    "Sundered Hills Region":"Earthlike",
    "Mudflats Region":"Swampy",
    "Mournhold Region":"Ashen",
    "Uld Vraech Region":"Ashen",
    "Dasek Marsh Region":"Swampy",
    "Ascadian Bluffs Region":"Ashen",
    "Reaver's Shore Region":"Earthlike",
    "Southern Gold Coast Region":"Earthlike",
    "Ascadian Isles Region":"Ashen",
    "R0_ar_Ald_Redaynia_Region":"Ashen",
    "Aranyon Pass Region":"Ashen",
    "Aanthirin Region":"Ashen",
    "Solitude Forest Region S":"Earthlike",
    "Midkarth Region":"Earthlike",
    "DD_3_Region":"Earthlike",
    "Vorndgad Forest Region":"Earthlike",
    "Velothi Mountains Region":"Ashen",
    "Solitude Forest Region":"Earthlike",
    "Troll's Teeth Mountains Region":"Earthlike"
  },
  "presets":{
    "Swampy":{
      "outscatter":[0.5325247608144,0.5098699579133,0.6145892865779],
      "Ashstorm":{
        "sunDayColor":[0,0,0],
        "skySunsetColor":[0.30993813276291,0.18211233615875,0.093341492116451],
        "fogSunsetColor":[0.2977246940136,0.18169410526752,0.13955387473106],
        "fogDayColor":[0.35936567187309,0.27649888396263,0.10618074983358],
        "skyNightColor":[0.1149712279439,0.085852406919003,0.041278012096882],
        "fogSunriseColor":[0.37065026164055,0.21653407812119,0.14376172423363],
        "ambientSunsetColor":[0.13612718880177,0.055234905332327,0.010615788400173],
        "skyDayColor":[0.40264835953712,0.28271782398224,0.14753814041615],
        "ambientDayColor":[0.085922762751579,0.060305539518595,0],
        "sunNightColor":[0.022389587014914,0.016157802194357,0],
        "ambientNightColor":[0.08727154135704,0.046069674193859,0],
        "sunSunsetColor":[0,0,0],
        "sundiscSunsetColor":[0.50196081399918,0.50196081399918,0.50196081399918],
        "cloudTexture":"Data Files\\Textures\\tew\\Watch the Skies\\ash\\tew_ash_12.dds",
        "ambientSunriseColor":[0.18482565879822,0.092812784016132,0.044765524566174],
        "sunSunriseColor":[0,0,0],
        "fogNightColor":[0.13948541879654,0.10534014552832,0.024669170379639],
        "skySunriseColor":[0.34003555774689,0.23040233552456,0.16985221207142]
      },
      "Blight":{
        "sunDayColor":[0,0,0],
        "skySunsetColor":[0.19808073341846,0.038061112165451,0.078213021159172],
        "fogSunsetColor":[0.18542429804802,0.076377123594284,0.093724936246872],
        "fogDayColor":[0.25345304608345,0.10045316815376,0.09570124745369],
        "skyNightColor":[0.11236551403999,0.0043255425989628,0],
        "fogSunriseColor":[0.21797166764736,0.12157221883535,0.11632417142391],
        "ambientSunsetColor":[0.12993742525578,0.047171771526337,0.043023735284805],
        "skyDayColor":[0.24774985015392,0.1164937838912,0.10803989320993],
        "ambientDayColor":[0.17313197255135,0.024405712261796,0.0035157692618668],
        "sunNightColor":[0.0060467356815934,0,0.0015626439126208],
        "ambientNightColor":[0.12279113382101,0.037491764873266,0.031458206474781],
        "sunSunsetColor":[0.0072888359427452,0,0],
        "sundiscSunsetColor":[0.50196081399918,0.50196081399918,0.50196081399918],
        "cloudTexture":"Data Files\\Textures\\tew\\Watch the Skies\\blight\\tew_blight_3.dds",
        "ambientSunriseColor":[0.15327446162701,0.051144324243069,0.025086680427194],
        "sunSunriseColor":[0.005916248075664,0,0.0029892369639128],
        "fogNightColor":[0.10797356814146,0.036608424037695,0.030659969896078],
        "skySunriseColor":[0.27824512124062,0.18122093379498,0.17619155347347]
      },
      "Foggy":{
        "sunDayColor":[0.0015762615948915,0,0],
        "skySunsetColor":[0.41186937689781,0.47676387429237,0.31257176399231],
        "fogSunsetColor":[0.60416400432587,0.38776278495789,0.35315877199173],
        "fogDayColor":[0.42937812209129,0.43656089901924,0.30153036117554],
        "skyNightColor":[0.07238681614399,0.086606688797474,0.046021964401007],
        "fogSunriseColor":[0.63805854320526,0.38942673802376,0.2721249461174],
        "ambientSunsetColor":[0.11852067708969,0.1138636469841,0],
        "skyDayColor":[0.35666072368622,0.40445852279663,0.27381670475006],
        "ambientDayColor":[0.1308925896883,0.15744069218636,0.070708185434341],
        "sunNightColor":[0,0,0],
        "ambientNightColor":[0.058337178081274,0.067509278655052,0.023645767942071],
        "sunSunsetColor":[0.39913076162338,0.11374911665916,0.046486292034388],
        "sundiscSunsetColor":[1,0.49159455299377,0.46142736077309],
        "cloudTexture":"Data Files\\Textures\\tew\\Watch the Skies\\foggy\\tew_foggy_1.dds",
        "ambientSunriseColor":[0.16963212192059,0.10485755652189,0.089205496013165],
        "sunSunriseColor":[0.43830952048302,0.19366009533405,0],
        "fogNightColor":[0.07507050037384,0.098320201039314,0.036613442003727],
        "skySunriseColor":[0.40025502443314,0.42479413747787,0.20345710217953]
      },
      "Blizzard":{
        "sunDayColor":[0.63921570777893,0.66274511814117,0.71764707565308],
        "skySunsetColor":[0.42352944612503,0.45098042488098,0.47450983524323],
        "fogSunsetColor":[0.42352944612503,0.45098042488098,0.47450983524323],
        "fogDayColor":[0.47450983524323,0.52156865596771,0.5686274766922],
        "skyNightColor":[0.10588236153126,0.11372549831867,0.12156863510609],
        "fogSunriseColor":[0.35686275362968,0.38823533058167,0.41568630933762],
        "ambientSunsetColor":[0.32549020648003,0.30196079611778,0.29411765933037],
        "skyDayColor":[0.47450983524323,0.52156865596771,0.5686274766922],
        "ambientDayColor":[0.3647058904171,0.37647062540054,0.41176474094391],
        "sunNightColor":[0.22352942824364,0.258823543787,0.29019609093666],
        "ambientNightColor":[0.20784315466881,0.24313727021217,0.27450981736183],
        "sunSunsetColor":[0.41568630933762,0.44705885648727,0.53333336114883],
        "sundiscSunsetColor":[0.50196081399918,0.50196081399918,0.50196081399918],
        "cloudTexture":"Data Files\\Textures\\tew\\Watch the Skies\\blizzard\\tew_blizzard_3.dds",
        "ambientSunriseColor":[0.32941177487373,0.34509804844856,0.36078432202339],
        "sunSunriseColor":[0.44705885648727,0.50196081399918,0.57254904508591],
        "fogNightColor":[0.082352943718433,0.094117656350136,0.10980392992496],
        "skySunriseColor":[0.35686275362968,0.38823533058167,0.41568630933762]
      },
      "Snow":{
        "sunDayColor":[0.63921570777893,0.66274511814117,0.71764707565308],
        "skySunsetColor":[0.37647062540054,0.45098042488098,0.52549022436142],
        "fogSunsetColor":[0.37647062540054,0.45098042488098,0.52549022436142],
        "fogDayColor":[0.60000002384186,0.61960786581039,0.65098041296005],
        "skyNightColor":[0.12156863510609,0.13725490868092,0.15294118225574],
        "fogSunriseColor":[0.41568630933762,0.35686275362968,0.35686275362968],
        "ambientSunsetColor":[0.27450981736183,0.3098039329052,0.34117648005486],
        "skyDayColor":[0.60000002384186,0.61960786581039,0.65098041296005],
        "ambientDayColor":[0.3647058904171,0.37647062540054,0.41176474094391],
        "sunNightColor":[0.21568629145622,0.258823543787,0.30196079611778],
        "ambientNightColor":[0.19215688109398,0.22745099663734,0.26666668057442],
        "sunSunsetColor":[0.39607846736908,0.47450983524323,0.55294120311737],
        "sundiscSunsetColor":[0.50196081399918,0.50196081399918,0.50196081399918],
        "cloudTexture":"Data Files\\Textures\\tx_bm_sky_snow.dds",
        "ambientSunriseColor":[0.36078432202339,0.32941177487373,0.32941177487373],
        "sunSunriseColor":[0.55294120311737,0.42745101451874,0.42745101451874],
        "fogNightColor":[0.12156863510609,0.13725490868092,0.15294118225574],
        "skySunriseColor":[0.41568630933762,0.35686275362968,0.35686275362968]
      },
      "Cloudy":{
        "sunDayColor":[0.54498076438904,0.50202906131744,0.30383998155594],
        "skySunsetColor":[0.43125355243683,0.4672417640686,0.17756931483746],
        "fogSunsetColor":[0.6938818693161,0.44875806570053,0.2965002655983],
        "fogDayColor":[0.59295481443405,0.61953908205032,0.5283197760582],
        "skyNightColor":[0.047359865158796,0.055884964764118,0],
        "fogSunriseColor":[0.78912472724915,0.54811173677444,0.32879090309143],
        "ambientSunsetColor":[0.29873311519623,0.18716745078564,0.10817515850067],
        "skyDayColor":[0.21791587769985,0.65532398223877,0.079334899783134],
        "ambientDayColor":[0.12870614230633,0.13404974341393,0.11532032489777],
        "sunNightColor":[0,0.00068269850453362,0],
        "ambientNightColor":[0,0.079097084701061,0.028330560773611],
        "sunSunsetColor":[0.74187684059143,0.30685031414032,0.17653149366379],
        "sundiscSunsetColor":[0.92726111412048,0,0.16537843644619],
        "cloudTexture":"Data Files\\Textures\\tew\\Watch the Skies\\cloudy\\tew_cloudy_14.dds",
        "ambientSunriseColor":[0.17880775034428,0.12768515944481,0.039444711059332],
        "sunSunriseColor":[0.54292899370193,0.25746083259583,0.012125955894589],
        "fogNightColor":[0.0079366797581315,0.064858824014664,0],
        "skySunriseColor":[0.50882303714752,0.56855744123459,0.31635415554047]
      },
      "Rain":{
        "sunDayColor":[3.9537881093565e-05,0,0],
        "skySunsetColor":[0.17930847406387,0.33691391348839,0.22713352739811],
        "fogSunsetColor":[0.25366002321243,0.29254376888275,0.36893686652184],
        "fogDayColor":[0.31006103754044,0.41381686925888,0.2958921790123],
        "skyNightColor":[0.059858459979296,0.086849123239517,0.080904185771942],
        "fogSunriseColor":[0.43147975206375,0.30045053362846,0.22514081001282],
        "ambientSunsetColor":[0.054995186626911,0.063603945076466,0.15069085359573],
        "skyDayColor":[0.24106334149837,0.45448535680771,0.26225200295448],
        "ambientDayColor":[0.17232823371887,0.2715485394001,0.14267259836197],
        "sunNightColor":[0,0,0.0021217896137387],
        "ambientNightColor":[0.039254445582628,0.07269125431776,0.06248252466321],
        "sunSunsetColor":[0.0027757303323597,0,0.009964969009161],
        "sundiscSunsetColor":[0.50196081399918,0.50196081399918,0.50196081399918],
        "cloudTexture":"Data Files\\Textures\\tx_sky_rainy.dds",
        "ambientSunriseColor":[0.21222126483917,0.090678073465824,0.051877304911613],
        "sunSunriseColor":[0.0030709677375853,0,0],
        "fogNightColor":[0.062812343239784,0.097583167254925,0.086415819823742],
        "skySunriseColor":[0.26878574490547,0.3201522231102,0.22216883301735]
      },
      "inscatter":[0.52277493299397,0.48679714382627,0.60834624846463],
      "Thunderstorm":{
        "sunDayColor":[0,0,0],
        "skySunsetColor":[0.18328800797462,0.058208379894495,0.078421056270599],
        "fogSunsetColor":[0.24570585787296,0.10269428789616,0.12831625342369],
        "fogDayColor":[0.1039252653718,0.29537630081177,0.2459712177515],
        "skyNightColor":[0.0370714366436,0.093584224581718,0.086650587618351],
        "fogSunriseColor":[0.2731646001339,0.15574876964092,0.13568705320358],
        "ambientSunsetColor":[0.13625358045101,0.072987958788872,0.081174552440643],
        "skyDayColor":[0.14078426361084,0.34564155340195,0.30170020461082],
        "ambientDayColor":[0.099249802529812,0.15769365429878,0.12803700566292],
        "sunNightColor":[0,0.036219958215952,0.039020348340273],
        "ambientNightColor":[0.054299078881741,0.074906438589096,0.080090306699276],
        "sunSunsetColor":[0,0,0],
        "sundiscSunsetColor":[0.50196081399918,0.50196081399918,0.50196081399918],
        "cloudTexture":"Data Files\\Textures\\tew\\Watch the Skies\\thunder\\tew_thunder_6.dds",
        "ambientSunriseColor":[0.15019407868385,0.04553647339344,0.057952255010605],
        "sunSunriseColor":[0,0,0],
        "fogNightColor":[0.048503190279007,0.094875372946262,0.083535119891167],
        "skySunriseColor":[0.22845381498337,0.12303126603365,0.072764821350574]
      },
      "Overcast":{
        "sunDayColor":[3.0499864806188e-05,0.00067833223147318,0],
        "skySunsetColor":[0.24567912518978,0.41699171066284,0.3298200070858],
        "fogSunsetColor":[0.45569062232971,0.40214660763741,0.45300582051277],
        "fogDayColor":[0.2861479818821,0.43001407384872,0.32507899403572],
        "skyNightColor":[0.041466694325209,0.061529211699963,0.052790284156799],
        "fogSunriseColor":[0.41256877779961,0.26538515090942,0.21854767203331],
        "ambientSunsetColor":[0.19241914153099,0.13517299294472,0.19704931974411],
        "skyDayColor":[0.088386304676533,0.30436813831329,0.22564898431301],
        "ambientDayColor":[0.1480320841074,0.23764988780022,0.17008018493652],
        "sunNightColor":[0,0,0],
        "ambientNightColor":[0.039136126637459,0.088547304272652,0.071837201714516],
        "sunSunsetColor":[0.0040308064781129,0,0.0064435685053468],
        "sundiscSunsetColor":[0.75068014860153,0.41769126057625,0.043899737298489],
        "cloudTexture":"Data Files\\Textures\\tew\\Watch the Skies\\overcast\\tew_overcast_6.dds",
        "ambientSunriseColor":[0.20883566141129,0.20564396679401,0.10201279819012],
        "sunSunriseColor":[0.0022109521087259,0,0],
        "fogNightColor":[0.023684518411756,0.073218502104282,0.048875067383051],
        "skySunriseColor":[0.28898611664772,0.33342599868774,0.17133310437202]
      },
      "Clear":{
        "sunDayColor":[0.83926010131836,0.84095406532288,0.5360661149025],
        "skySunsetColor":[0.42703351378441,0.4647861123085,0.33950990438461],
        "fogSunsetColor":[0.73902469873428,0.51812297105789,0.46147102117538],
        "fogDayColor":[0.6270124912262,0.74644374847412,0.46187075972557],
        "skyNightColor":[0.0059575284831226,0.0912926197052,0.030812595039606],
        "fogSunriseColor":[0.846943795681,0.58612775802612,0.45298188924789],
        "ambientSunsetColor":[0.27077010273933,0.10091215372086,0.094704024493694],
        "skyDayColor":[0.48462039232254,0.73491114377975,0.49330750107765],
        "ambientDayColor":[0.056345295161009,0.066939420998096,0.058079838752747],
        "sunNightColor":[0.0022569480352104,0,0],
        "ambientNightColor":[0.051280442625284,0.086676351726055,0.053171996027231],
        "sunSunsetColor":[0.93112689256668,0.36986580491066,0.34310242533684],
        "sundiscSunsetColor":[1,0.7330407500267,0.54886901378632],
        "cloudTexture":"Data Files\\Textures\\tew\\Watch the Skies\\clear\\tew_clear_12.dds",
        "ambientSunriseColor":[0.14112740755081,0.12367699295282,0.006975925527513],
        "sunSunriseColor":[0.80209499597549,0.39034348726273,0.013009670190513],
        "fogNightColor":[0.046380408108234,0.073728695511818,0.051824130117893],
        "skySunriseColor":[0.52029538154602,0.60511672496796,0.34112906455994]
      }
    },
    "Reddish":{
      "outscatter":[0.18056986446548,0.45947428197135,0.57177939832843],
      "Ashstorm":{
        "sunDayColor":[0.0016352871898562,0,0],
        "skySunsetColor":[0.36932337284088,0.15772472321987,0.066326715052128],
        "fogSunsetColor":[0.47730404138565,0.21341656148434,0.18512488901615],
        "fogDayColor":[0.37062880396843,0.25324693322182,0.091725379228592],
        "skyNightColor":[0.19717943668365,0.099539287388325,0.063329197466373],
        "fogSunriseColor":[0.48016232252121,0.1735768020153,0.13432140648365],
        "ambientSunsetColor":[0.16596879065037,0.071004718542099,0.07745710760355],
        "skyDayColor":[0.29486298561096,0.18773190677166,0.055789448320866],
        "ambientDayColor":[0.18029430508614,0.11416651308537,0.023400086909533],
        "sunNightColor":[0.0039368867874146,0,0],
        "ambientNightColor":[0.16369986534119,0.066555887460709,0.0042689051479101],
        "sunSunsetColor":[0.005481225438416,0,0],
        "sundiscSunsetColor":[0.79976499080658,0.11123460531235,0],
        "cloudTexture":"Data Files\\Textures\\tew\\Watch the Skies\\ash\\tew_ash_12.dds",
        "ambientSunriseColor":[0.26682969927788,0.087721928954124,0.054876130074263],
        "sunSunriseColor":[0,0,0],
        "fogNightColor":[0.20123420655727,0.11595976352692,0.063529469072819],
        "skySunriseColor":[0.40012675523758,0.10350848734379,0.083014160394669]
      },
      "Blight":{
        "sunDayColor":[0,0,0],
        "skySunsetColor":[0.18057057261467,0.091319963335991,0.04847089573741],
        "fogSunsetColor":[0.18571262061596,0.10915699601173,0.068606339395046],
        "fogDayColor":[0.2396148443222,0.10392232984304,0.071055926382542],
        "skyNightColor":[0.32506653666496,0.14246761798859,0.15079393982887],
        "fogSunriseColor":[0.28650411963463,0.14478819072247,0.12430088967085],
        "ambientSunsetColor":[0.25480303168297,0.15475477278233,0.086740598082542],
        "skyDayColor":[0.14155973494053,0.062535263597965,0.037193339318037],
        "ambientDayColor":[0.13081000745296,0.045698687434196,0],
        "sunNightColor":[0.044916965067387,0.020021503791213,0],
        "ambientNightColor":[0.19709004461765,0.10084059089422,0.094825074076653],
        "sunSunsetColor":[0,0,0],
        "sundiscSunsetColor":[0.50196081399918,0.50196081399918,0.50196081399918],
        "cloudTexture":"Data Files\\Textures\\tew\\Watch the Skies\\blight\\tew_blight_1.dds",
        "ambientSunriseColor":[0.14769516885281,0.051402028650045,0.033865217119455],
        "sunSunriseColor":[0.0060201692394912,0,0.00032863669912331],
        "fogNightColor":[0.11756660044193,0.030380612239242,0.029102029278874],
        "skySunriseColor":[0.26187321543694,0.10199784487486,0.10660539567471]
      },
      "Foggy":{
        "sunDayColor":[0.18922086060047,0.09281349927187,0],
        "skySunsetColor":[0.45990121364594,0.064512148499489,0.054561872035265],
        "fogSunsetColor":[0.45890393853188,0.21104604005814,0.1489705145359],
        "fogDayColor":[0.57148712873459,0.36562639474869,0.22508439421654],
        "skyNightColor":[0.12959124147892,0.030287535861135,0],
        "fogSunriseColor":[0.7716817855835,0.31792119145393,0.23866441845894],
        "ambientSunsetColor":[0.18541267514229,0.038258299231529,0.0091168126091361],
        "skyDayColor":[0.57066988945007,0.3467615544796,0.25136610865593],
        "ambientDayColor":[0.144156858325,0.083503447473049,0.028893770650029],
        "sunNightColor":[0.048979517072439,0.0075960932299495,0],
        "ambientNightColor":[0.12074908614159,0.020187869668007,0],
        "sunSunsetColor":[0.32357284426689,0.052266668528318,0],
        "sundiscSunsetColor":[1,0.55042725801468,0.33381456136703],
        "cloudTexture":"Data Files\\Textures\\tew\\Watch the Skies\\foggy\\tew_foggy_7.dds",
        "ambientSunriseColor":[0.34587335586548,0.17865712940693,0.14074292778969],
        "sunSunriseColor":[0.57485443353653,0.20717133581638,0.057432390749454],
        "fogNightColor":[0.15356855094433,0.0047676465474069,0],
        "skySunriseColor":[0.7700589299202,0.42248833179474,0.31794512271881]
      },
      "Blizzard":{
        "sunDayColor":[0.63921570777893,0.66274511814117,0.71764707565308],
        "skySunsetColor":[0.42352944612503,0.45098042488098,0.47450983524323],
        "fogSunsetColor":[0.42352944612503,0.45098042488098,0.47450983524323],
        "fogDayColor":[0.47450983524323,0.52156865596771,0.5686274766922],
        "skyNightColor":[0.10588236153126,0.11372549831867,0.12156863510609],
        "fogSunriseColor":[0.35686275362968,0.38823533058167,0.41568630933762],
        "ambientSunsetColor":[0.32549020648003,0.30196079611778,0.29411765933037],
        "skyDayColor":[0.47450983524323,0.52156865596771,0.5686274766922],
        "ambientDayColor":[0.3647058904171,0.37647062540054,0.41176474094391],
        "sunNightColor":[0.22352942824364,0.258823543787,0.29019609093666],
        "ambientNightColor":[0.20784315466881,0.24313727021217,0.27450981736183],
        "sunSunsetColor":[0.41568630933762,0.44705885648727,0.53333336114883],
        "sundiscSunsetColor":[0.50196081399918,0.50196081399918,0.50196081399918],
        "cloudTexture":"Data Files\\Textures\\tew\\Watch the Skies\\blizzard\\tew_blizzard_6.dds",
        "ambientSunriseColor":[0.32941177487373,0.34509804844856,0.36078432202339],
        "sunSunriseColor":[0.44705885648727,0.50196081399918,0.57254904508591],
        "fogNightColor":[0.082352943718433,0.094117656350136,0.10980392992496],
        "skySunriseColor":[0.35686275362968,0.38823533058167,0.41568630933762]
      },
      "Snow":{
        "sunDayColor":[0.63921570777893,0.66274511814117,0.71764707565308],
        "skySunsetColor":[0.37647062540054,0.45098042488098,0.52549022436142],
        "fogSunsetColor":[0.37647062540054,0.45098042488098,0.52549022436142],
        "fogDayColor":[0.60000002384186,0.61960786581039,0.65098041296005],
        "skyNightColor":[0.12156863510609,0.13725490868092,0.15294118225574],
        "fogSunriseColor":[0.41568630933762,0.35686275362968,0.35686275362968],
        "ambientSunsetColor":[0.27450981736183,0.3098039329052,0.34117648005486],
        "skyDayColor":[0.60000002384186,0.61960786581039,0.65098041296005],
        "ambientDayColor":[0.3647058904171,0.37647062540054,0.41176474094391],
        "sunNightColor":[0.21568629145622,0.258823543787,0.30196079611778],
        "ambientNightColor":[0.19215688109398,0.22745099663734,0.26666668057442],
        "sunSunsetColor":[0.39607846736908,0.47450983524323,0.55294120311737],
        "sundiscSunsetColor":[0.50196081399918,0.50196081399918,0.50196081399918],
        "cloudTexture":"Data Files\\Textures\\tew\\Watch the Skies\\snow\\tew_snow_2.dds",
        "ambientSunriseColor":[0.36078432202339,0.32941177487373,0.32941177487373],
        "sunSunriseColor":[0.55294120311737,0.42745101451874,0.42745101451874],
        "fogNightColor":[0.12156863510609,0.13725490868092,0.15294118225574],
        "skySunriseColor":[0.41568630933762,0.35686275362968,0.35686275362968]
      },
      "Cloudy":{
        "sunDayColor":[0.86629736423492,0.74882566928864,0.45876207947731],
        "skySunsetColor":[0.72122043371201,0.29540440440178,0],
        "fogSunsetColor":[0.63351595401764,0.39724153280258,0.42175903916359],
        "fogDayColor":[0.93909567594528,0.6502867937088,0.54561346769333],
        "skyNightColor":[0.1187154725194,0.069772019982338,0.046231582760811],
        "fogSunriseColor":[0.90629249811172,0.59665536880493,0.50538069009781],
        "ambientSunsetColor":[0.2365550249815,0.12696033716202,0.053951248526573],
        "skyDayColor":[0.90948385000229,0.59274637699127,0],
        "ambientDayColor":[0.20518597960472,0.17106518149376,0.089749567210674],
        "sunNightColor":[0.00012685495312326,0.00056759809376672,0],
        "ambientNightColor":[0.10911197960377,0.086030833423138,0.02183748036623],
        "sunSunsetColor":[0.92411369085312,0.33307561278343,0.27461928129196],
        "sundiscSunsetColor":[0.89069545269012,0.2459509074688,0.090609103441238],
        "cloudTexture":"Data Files\\Textures\\tew\\Watch the Skies\\cloudy\\tew_cloudy_4.dds",
        "ambientSunriseColor":[0.16640277206898,0.064124934375286,0.013540874235332],
        "sunSunriseColor":[0.88139241933823,0.33763861656189,0.14939332008362],
        "fogNightColor":[0.14019142091274,0.088386110961437,0.023960497230291],
        "skySunriseColor":[0.66321057081223,0.39622086286545,0.16224853694439]
      },
      "Rain":{
        "sunDayColor":[0.001640033791773,0,0],
        "skySunsetColor":[0.37434747815132,0.11669924855232,0.17467515170574],
        "fogSunsetColor":[0.33042988181114,0.1783841252327,0.19805717468262],
        "fogDayColor":[0.39250230789185,0.26063483953476,0.13313448429108],
        "skyNightColor":[0.13323949277401,0.073138788342476,0.0064581073820591],
        "fogSunriseColor":[0.41618433594704,0.21997478604317,0.17199932038784],
        "ambientSunsetColor":[0.27141353487968,0.069976791739464,0.079213574528694],
        "skyDayColor":[0.29514381289482,0.20563444495201,0.14236558973789],
        "ambientDayColor":[0.16385166347027,0.10520940274,0.01530403457582],
        "sunNightColor":[0.0031171101145446,0,0],
        "ambientNightColor":[0.14081138372421,0.042907409369946,0.0033573203254491],
        "sunSunsetColor":[0,0,0],
        "sundiscSunsetColor":[0.50196081399918,0.50196081399918,0.50196081399918],
        "cloudTexture":"Data Files\\Textures\\tew\\Watch the Skies\\rain\\tew_rain_9.dds",
        "ambientSunriseColor":[0.24213515222073,0.086429618299007,0.034932281821966],
        "sunSunriseColor":[0.0044009354896843,0,0],
        "fogNightColor":[0.14197923243046,0.092856824398041,0.057066269218922],
        "skySunriseColor":[0.36497217416763,0.17570970952511,0.13060465455055]
      },
      "inscatter":[0.065588639173655,0.40930828375408,0.67381081267788],
      "Thunderstorm":{
        "sunDayColor":[0.0036706202663481,0,0],
        "skySunsetColor":[0.19667734205723,0.11291207373142,0.1889550536871],
        "fogSunsetColor":[0.35310447216034,0.26517850160599,0.31686726212502],
        "fogDayColor":[0.39185628294945,0.23229499161243,0.19737112522125],
        "skyNightColor":[0.14605607092381,0.10672891885042,0.068513035774231],
        "fogSunriseColor":[0.34480434656143,0.17937158048153,0.25709265470505],
        "ambientSunsetColor":[0.1533545255661,0.059409167617559,0.14974157512188],
        "skyDayColor":[0.31465002894402,0.17308343946934,0.1300904750824],
        "ambientDayColor":[0.19425417482853,0.098354503512383,0.049225144088268],
        "sunNightColor":[0.059283066540956,0.031542006880045,0],
        "ambientNightColor":[0.11625704169273,0.086403854191303,0.022971302270889],
        "sunSunsetColor":[0,0,0],
        "sundiscSunsetColor":[0.50196081399918,0.50196081399918,0.50196081399918],
        "cloudTexture":"Data Files\\Textures\\tew\\Watch the Skies\\thunder\\tew_thunder_8.dds",
        "ambientSunriseColor":[0.15096645057201,0.035793669521809,0.083151578903198],
        "sunSunriseColor":[0.0067760092206299,0,0.00045767691335641],
        "fogNightColor":[0.15120068192482,0.10822221636772,0.063547194004059],
        "skySunriseColor":[0.23398266732693,0.10445623099804,0.0754614174366]
      },
      "Overcast":{
        "sunDayColor":[0.0033318644855171,0,0],
        "skySunsetColor":[0.34972307085991,0.12487039715052,0.050651140511036],
        "fogSunsetColor":[0.31101167201996,0.053168773651123,0.064251802861691],
        "fogDayColor":[0.38226252794266,0.20598517358303,0.10213229060173],
        "skyNightColor":[0.099955685436726,0.0060599213466048,0],
        "fogSunriseColor":[0.27644574642181,0.067513212561607,0.042088430374861],
        "ambientSunsetColor":[0.27248486876488,0.066517390310764,0.096982292830944],
        "skyDayColor":[0.29911097884178,0.12372154742479,0.043713729828596],
        "ambientDayColor":[0.33166894316673,0.16389717161655,0.012668052688241],
        "sunNightColor":[0.0043694437481463,0,0],
        "ambientNightColor":[0.094459407031536,0.014785900712013,0],
        "sunSunsetColor":[0,0,0],
        "sundiscSunsetColor":[0.36423671245575,0.035929270088673,0],
        "cloudTexture":"Data Files\\Textures\\tew\\Watch the Skies\\overcast\\tew_overcast_6.dds",
        "ambientSunriseColor":[0.39212512969971,0.17075991630554,0.1202250868082],
        "sunSunriseColor":[0.004689006600529,0,0],
        "fogNightColor":[0.10003214329481,0.021743785589933,0.0066970926709473],
        "skySunriseColor":[0.52758592367172,0.32940286397934,0.19926142692566]
      },
      "Clear":{
        "sunDayColor":[0.99510616064072,0.8656679391861,0.69291323423386],
        "skySunsetColor":[0.83584886789322,0.4782238304615,0.16683110594749],
        "fogSunsetColor":[0.76982337236404,0.51406592130661,0.43533530831337],
        "fogDayColor":[0.88490831851959,0.83067440986633,0.77590376138687],
        "skyNightColor":[0.14692898094654,0.049277041107416,0],
        "fogSunriseColor":[0.86572933197021,0.48809495568275,0.31713938713074],
        "ambientSunsetColor":[0.36566877365112,0.15956845879555,0.14972089231014],
        "skyDayColor":[0.94379639625549,0.68498647212982,0],
        "ambientDayColor":[0.30549004673958,0.18514861166477,0.079766884446144],
        "sunNightColor":[0.0028415368869901,0,0],
        "ambientNightColor":[0.12371070683002,0.076945573091507,0.018587363883853],
        "sunSunsetColor":[0.65094971656799,0.27261105179787,0.14953452348709],
        "sundiscSunsetColor":[1,0.74246025085449,0.56796211004257],
        "cloudTexture":"Data Files\\Textures\\tew\\Watch the Skies\\clear\\tew_clear_7.dds",
        "ambientSunriseColor":[0.24476040899754,0.14862267673016,0.123703956604],
        "sunSunriseColor":[0.86463212966919,0.35210955142975,0.18789733946323],
        "fogNightColor":[0.14791418612003,0.076270885765553,0.056155648082495],
        "skySunriseColor":[0.75868481397629,0.42595106363297,0]
      }
    },
    "Ashen":{
      "outscatter":[0.51008780904226,0.51135926500821,0.61565477373834],
      "Ashstorm":{
        "sunDayColor":[0.0013100667856634,0,0],
        "skySunsetColor":[0.20712295174599,0.083529002964497,0.082012981176376],
        "fogSunsetColor":[0.25517594814301,0.10680146515369,0.10976802557707],
        "fogDayColor":[0.31113284826279,0.21562264859676,0.10238434374332],
        "skyNightColor":[0.13064490258694,0.095331773161888,0.045040648430586],
        "fogSunriseColor":[0.25036737322807,0.10376466065645,0.084998145699501],
        "ambientSunsetColor":[0.1081330254674,0.031233822926879,0.027737284079194],
        "skyDayColor":[0.29650178551674,0.19528034329414,0.11853252351284],
        "ambientDayColor":[0.10352556407452,0.056385133415461,0.0048656067810953],
        "sunNightColor":[0,0,0],
        "ambientNightColor":[0.075412020087242,0.040336649864912,0.0070139728486538],
        "sunSunsetColor":[0,0,0],
        "sundiscSunsetColor":[0.62189120054245,0.46802350878716,0.40424281358719],
        "cloudTexture":"Data Files\\Textures\\tew\\Watch the Skies\\ash\\tew_ash_3.dds",
        "sunSunriseColor":[0,0,0],
        "ambientSunriseColor":[0.11021277308464,0.021139934659004,0.0046307151205838],
        "fogNightColor":[0.10132434219122,0.068529345095158,0.019162826240063],
        "skySunriseColor":[0.29002973437309,0.091181166470051,0.059809118509293]
      },
      "Blight":{
        "sunDayColor":[0.013191251084208,0,0],
        "skySunsetColor":[0.15210545063019,0.0098805967718363,0.065427601337433],
        "fogSunsetColor":[0.16567321121693,0.042447280138731,0.092728823423386],
        "fogDayColor":[0.25261855125427,0.075639277696609,0.054065149277449],
        "skyNightColor":[0.16292230784893,0.049560233950615,0.060714781284332],
        "fogSunriseColor":[0.19434422254562,0.056736584752798,0.086649604141712],
        "ambientSunsetColor":[0.11611268669367,0.027635941281915,0.061960194259882],
        "skyDayColor":[0.21533311903477,0.065663583576679,0.053630102425814],
        "ambientDayColor":[0.13076739013195,0.020245768129826,0.03365895152092],
        "sunNightColor":[0,0,0],
        "ambientNightColor":[0.10654941946268,0.016822198405862,0.016011925414205],
        "sunSunsetColor":[0.0040972642600536,0,0.00080017605796456],
        "sundiscSunsetColor":[0.50196081399918,0.50196081399918,0.50196081399918],
        "cloudTexture":"Data Files\\Textures\\tew\\Watch the Skies\\blight\\tew_blight_4.dds",
        "sunSunriseColor":[0.0055059813894331,0,0.003679635701701],
        "ambientSunriseColor":[0.080962285399437,0.013814529404044,0.024061733856797],
        "fogNightColor":[0.091586567461491,0.014651418663561,0.015198251232505],
        "skySunriseColor":[0.19287617504597,0.037174474447966,0.085486195981503]
      },
      "Foggy":{
        "sunDayColor":[0.11646833270788,0.11645316332579,0.1164510846138],
        "skySunsetColor":[0.34253758192062,0.18383841216564,0.15532936155796],
        "fogSunsetColor":[0.46117451786995,0.20290786027908,0.2205915004015],
        "fogDayColor":[0.10560031235218,0.50846916437149,0.49507594108582],
        "skyNightColor":[0,0.073069587349892,0.067676812410355],
        "fogSunriseColor":[0.75002002716064,0.32868927717209,0.33183345198631],
        "ambientSunsetColor":[0.1861873716116,0.036474652588367,0.018611552193761],
        "skyDayColor":[0,0.45375874638557,0.42150118947029],
        "ambientDayColor":[0.054758571088314,0.10551141947508,0.10839176923037],
        "sunNightColor":[0,0.00029008477577008,0.00025824338081293],
        "ambientNightColor":[0,0.061887204647064,0.064265973865986],
        "sunSunsetColor":[0.16312883794308,0.026389824226499,0.029890196397901],
        "sundiscSunsetColor":[1,0.55042725801468,0.33381456136703],
        "cloudTexture":"Data Files\\Textures\\tew\\Watch the Skies\\foggy\\tew_foggy_5.dds",
        "sunSunriseColor":[0.52334606647491,0.24808284640312,0.13757345080376],
        "ambientSunriseColor":[0.29152280092239,0.20310404896736,0.19324116408825],
        "fogNightColor":[0,0.069717854261398,0.065776512026787],
        "skySunriseColor":[0.73585546016693,0.42901545763016,0.47623318433762]
      },
      "inscatter":[0.47855061986677,0.49877270808042,0.61895772552918],
      "Snow":{
        "sunDayColor":[0,0.00042822692194022,0.0011106133460999],
        "skySunsetColor":[0.37647062540054,0.45098042488098,0.52549022436142],
        "fogSunsetColor":[0.37647062540054,0.45098042488098,0.52549022436142],
        "fogDayColor":[0.23274993896484,0.38813310861588,0.51699829101563],
        "skyNightColor":[0.058291904628277,0.076103568077087,0.092234045267105],
        "fogSunriseColor":[0.41568630933762,0.35686275362968,0.35686275362968],
        "ambientSunsetColor":[0.27450981736183,0.3098039329052,0.34117648005486],
        "skyDayColor":[0.057793669402599,0.15549145638943,0.2078056037426],
        "ambientDayColor":[0.079855717718601,0.30316710472107,0.5486803650856],
        "sunNightColor":[0.15749657154083,0.084963537752628,0.061697646975517],
        "ambientNightColor":[0.07368241250515,0.073822490870953,0.075437001883984],
        "sunSunsetColor":[0,0.51057249307632,0.7659747004509],
        "sundiscSunsetColor":[0.50196081399918,0.50196081399918,0.50196081399918],
        "cloudTexture":"Data Files\\Textures\\tew\\Watch the Skies\\snow\\tew_snow_4.dds",
        "sunSunriseColor":[0.47102963924408,0.39935764670372,0.40422892570496],
        "ambientSunriseColor":[0.36078432202339,0.32941177487373,0.32941177487373],
        "fogNightColor":[0.0095124440267682,0.035137310624123,0.059773858636618],
        "skySunriseColor":[0.41568630933762,0.35686275362968,0.35686275362968]
      },
      "Cloudy":{
        "sunDayColor":[0.77279931306839,0.59227955341339,0.44576388597488],
        "skySunsetColor":[0.17494787275791,0.49211075901985,0.47663834691048],
        "fogSunsetColor":[0.68437272310257,0.44963642954826,0.35513538122177],
        "fogDayColor":[0.53719311952591,0.74394285678864,0.82157623767853],
        "skyNightColor":[0,0.061672531068325,0.068611435592175],
        "fogSunriseColor":[0.6906470656395,0.57514649629593,0.5322847366333],
        "ambientSunsetColor":[0.29873311519623,0.18716745078564,0.10817515850067],
        "skyDayColor":[0.37506091594696,0.81877940893173,0.68906831741333],
        "ambientDayColor":[0.14376522600651,0.1736011505127,0.17658619582653],
        "sunNightColor":[0,0.00073516799602658,0.00087825115770102],
        "ambientNightColor":[0,0.07527282834053,0.082327403128147],
        "sunSunsetColor":[0.74151134490967,0.37895095348358,0.26459118723869],
        "sundiscSunsetColor":[0.92726111412048,0,0.16537843644619],
        "cloudTexture":"Data Files\\Textures\\tew\\Watch the Skies\\cloudy\\tew_cloudy_3.dds",
        "sunSunriseColor":[0.49243861436844,0.34023371338844,0.23999197781086],
        "ambientSunriseColor":[0.17880775034428,0.12768515944481,0.039444711059332],
        "fogNightColor":[0,0.06147263944149,0.066727377474308],
        "skySunriseColor":[0,0.60787814855576,0.57909935712814]
      },
      "Rain":{
        "sunDayColor":[0,0.00030193509883247,0],
        "skySunsetColor":[0.2044742256403,0.15023481845856,0.14963483810425],
        "fogSunsetColor":[0.37914395332336,0.14759354293346,0.15991389751434],
        "fogDayColor":[0.00015014379459899,0.34356588125229,0.38266709446907],
        "skyNightColor":[0,0.08125626295805,0.096069186925888],
        "fogSunriseColor":[0.42065185308456,0.22028908133507,0.12427321821451],
        "ambientSunsetColor":[0.16576859354973,0.055922843515873,0.065438687801361],
        "skyDayColor":[0.012446613050997,0.33196294307709,0.39547580480576],
        "ambientDayColor":[0.11950786411762,0.20025680959225,0.20503462851048],
        "sunNightColor":[0,0.00040306430310011,0.0025957387406379],
        "ambientNightColor":[0.036403127014637,0.065373457968235,0.098504886031151],
        "sunSunsetColor":[0.011233375407755,0,0],
        "sundiscSunsetColor":[0.50196081399918,0.50196081399918,0.50196081399918],
        "cloudTexture":"Data Files\\Textures\\tew\\Watch the Skies\\rain\\tew_rain_6.dds",
        "sunSunriseColor":[0.0030709677375853,0,0],
        "ambientSunriseColor":[0.20087294280529,0.09811782091856,0.051138672977686],
        "fogNightColor":[0.0100501421839,0.083041861653328,0.11049216985703],
        "skySunriseColor":[0.43616205453873,0.25107434391975,0.18392649292946]
      },
      "Blizzard":{
        "sunDayColor":[0.66544038057327,0.50719028711319,0.40263193845749],
        "skySunsetColor":[0.42352944612503,0.45098042488098,0.47450983524323],
        "fogSunsetColor":[0.42352944612503,0.45098042488098,0.47450983524323],
        "fogDayColor":[0.47450983524323,0.52156865596771,0.5686274766922],
        "skyNightColor":[0,0.049959328025579,0.087564893066883],
        "fogSunriseColor":[0.35686275362968,0.38823533058167,0.41568630933762],
        "ambientSunsetColor":[0.32549020648003,0.30196079611778,0.29411765933037],
        "skyDayColor":[0.37115970253944,0.38333266973495,0.39497196674347],
        "ambientDayColor":[0.3647058904171,0.37647062540054,0.41176474094391],
        "sunNightColor":[0,0.00053495465544984,0.0023880638182163],
        "ambientNightColor":[0.0096400259062648,0.048360593616962,0.078337356448174],
        "sunSunsetColor":[0,0.47355967760086,0.68990421295166],
        "sundiscSunsetColor":[0.50196081399918,0.50196081399918,0.50196081399918],
        "cloudTexture":"Data Files\\Textures\\tew\\Watch the Skies\\blizzard\\tew_blizzard_4.dds",
        "sunSunriseColor":[0.36316761374474,0.42337238788605,0.4822770357132],
        "ambientSunriseColor":[0.32941177487373,0.34509804844856,0.36078432202339],
        "fogNightColor":[0,0.035677127540112,0.079155750572681],
        "skySunriseColor":[0.35686275362968,0.38823533058167,0.41568630933762]
      },
      "Thunderstorm":{
        "sunDayColor":[0,0,0.0081910500302911],
        "skySunsetColor":[0.26606565713882,0.093609653413296,0.1750180721283],
        "fogSunsetColor":[0.22305533289909,0.10737722367048,0.14462698996067],
        "fogDayColor":[0.042387515306473,0.27978619933128,0.39470019936562],
        "skyNightColor":[0.028121665120125,0.067184068262577,0.097938008606434],
        "fogSunriseColor":[0.24185548722744,0.12558999657631,0.092546552419662],
        "ambientSunsetColor":[0.091471448540688,0.037197791039944,0.062705121934414],
        "skyDayColor":[0.11733844131231,0.27505508065224,0.38403159379959],
        "ambientDayColor":[0.11538075655699,0.1739517301321,0.24841822683811],
        "sunNightColor":[0,0,0],
        "ambientNightColor":[0.043998625129461,0.047472100704908,0.088868871331215],
        "sunSunsetColor":[0.0030810551252216,0,0],
        "sundiscSunsetColor":[0.50196081399918,0.50196081399918,0.50196081399918],
        "cloudTexture":"Data Files\\Textures\\tew\\Watch the Skies\\thunder\\tew_thunder_5.dds",
        "sunSunriseColor":[0.0040470031090081,0,0],
        "ambientSunriseColor":[0.10016552358866,0.042506236582994,0.019094375893474],
        "fogNightColor":[0.047006938606501,0.075397849082947,0.11669899523258],
        "skySunriseColor":[0.27482560276985,0.18806952238083,0.15177702903748]
      },
      "Overcast":{
        "sunDayColor":[3.0499864806188e-05,0.00067833223147318,0],
        "skySunsetColor":[0.28285452723503,0.23291155695915,0.31788590550423],
        "fogSunsetColor":[0.30171376466751,0.25358960032463,0.3350658416748],
        "fogDayColor":[0.15455909073353,0.46405616402626,0.47385317087173],
        "skyNightColor":[0,0.082157798111439,0.078631460666656],
        "fogSunriseColor":[0.37856978178024,0.20526334643364,0.15093842148781],
        "ambientSunsetColor":[0.12144764512777,0.036749333143234,0.088883601129055],
        "skyDayColor":[0.17980043590069,0.36593985557556,0.3434391617775],
        "ambientDayColor":[0.15411372482777,0.2396479845047,0.24198630452156],
        "sunNightColor":[6.901822052896e-05,0.00048712574061938,0],
        "ambientNightColor":[0.060109194368124,0.060099013149738,0.060097619891167],
        "sunSunsetColor":[0.0040308064781129,0,0.0064435685053468],
        "sundiscSunsetColor":[0.75068014860153,0.41769126057625,0.043899737298489],
        "cloudTexture":"Data Files\\Textures\\tew\\Watch the Skies\\overcast\\tew_overcast_5.dds",
        "sunSunriseColor":[0,0,0],
        "ambientSunriseColor":[0.13205061852932,0.04478232562542,0],
        "fogNightColor":[0.057147894054651,0.10090432316065,0.092678435146809],
        "skySunriseColor":[0.12166617065668,0.21201068162918,0.2051110714674]
      },
      "Clear":{
        "sunDayColor":[0.89339393377304,0.82049006223679,0.66756767034531],
        "skySunsetColor":[0.31585058569908,0.48227116465569,0.45178291201591],
        "fogSunsetColor":[0.73739868402481,0.51530301570892,0.46008250117302],
        "fogDayColor":[0.45659229159355,0.75641423463821,0.79214215278625],
        "skyNightColor":[0,0.086679369211197,0.092945262789726],
        "fogSunriseColor":[0.80882787704468,0.59304457902908,0.49442180991173],
        "ambientSunsetColor":[0.27200320363045,0.10196992009878,0.095693707466125],
        "skyDayColor":[0.091098710894585,0.75256502628326,0.77607440948486],
        "ambientDayColor":[0.060680508613586,0.073150508105755,0.064310178160667],
        "sunNightColor":[0.0022647432051599,0,0],
        "ambientNightColor":[0.025126231834292,0.087776564061642,0.10094147920609],
        "sunSunsetColor":[0.92756348848343,0.36444607377052,0.3387266099453],
        "sundiscSunsetColor":[1,0.72896105051041,0.54059851169586],
        "cloudTexture":"Data Files\\Textures\\tew\\Watch the Skies\\clear\\tew_clear_16.dds",
        "sunSunriseColor":[0.70876652002335,0.42359173297882,0.2741514146328],
        "ambientSunriseColor":[0.15766987204552,0.11597593128681,0.06558483093977],
        "fogNightColor":[0.035948641598225,0.078010812401772,0.086769744753838],
        "skySunriseColor":[0.25656616687775,0.59936565160751,0.79266285896301]
      }
    },
    "Earthlike":{
      "outscatter":[0.18085375289281,0.45512381701593,0.86192741440734],
      "Ashstorm":{
        "sunDayColor":[0.89411771297455,0.54509806632996,0.44705885648727],
        "skySunsetColor":[0.41568630933762,0.21568629145622,0.15686275064945],
        "fogSunsetColor":[0.41568630933762,0.21568629145622,0.15686275064945],
        "fogDayColor":[0.48627454042435,0.28627452254295,0.22745099663734],
        "skyNightColor":[0.086577109992504,0.080737762153149,0.078097857534885],
        "cloudTexture":"Data Files\\Textures\\tew\\Watch the Skies\\ash\\tew_ash_4.dds",
        "ambientSunsetColor":[0.18823531270027,0.15294118225574,0.13725490868092],
        "skyDayColor":[0.48627454042435,0.28627452254295,0.22745099663734],
        "ambientDayColor":[0.29411765933037,0.19215688109398,0.16078431904316],
        "sunNightColor":[0,0,0],
        "sunSunriseColor":[0.72156864404678,0.35686275362968,0.27843138575554],
        "sunSunsetColor":[0.72549021244049,0.33725491166115,0.22352942824364],
        "sundiscSunsetColor":[0.50196081399918,0.50196081399918,0.50196081399918],
        "ambientSunriseColor":[0.21176472306252,0.16470588743687,0.14509804546833],
        "fogSunriseColor":[0.35686275362968,0.21960785984993,0.20000001788139],
        "ambientNightColor":[0.15529862046242,0.12301257997751,0.10552898049355],
        "fogNightColor":[0.086577109992504,0.080737762153149,0.078097857534885],
        "skySunriseColor":[0.35686275362968,0.21960785984993,0.20000001788139]
      },
      "Blight":{
        "sunDayColor":[0.87843143939972,0.32941177487373,0.32941177487373],
        "skySunsetColor":[0.36078432202339,0.1294117718935,0.1294117718935],
        "fogSunsetColor":[0.36078432202339,0.1294117718935,0.1294117718935],
        "fogDayColor":[0.50196081399918,0.074509806931019,0.074509806931019],
        "skyNightColor":[0.17254902422428,0.054901964962482,0.054901964962482],
        "cloudTexture":"Data Files\\Textures\\tew\\Watch the Skies\\blight\\tew_blight_4.dds",
        "ambientSunsetColor":[0.23921570181847,0.15686275064945,0.15686275064945],
        "skyDayColor":[0.35294118523598,0.13725490868092,0.13725490868092],
        "ambientDayColor":[0.3098039329052,0.21176472306252,0.21176472306252],
        "sunNightColor":[0,0,0],
        "sunSunriseColor":[0.70588237047195,0.30588236451149,0.30588236451149],
        "sunSunsetColor":[0.70588237047195,0.30588236451149,0.30588236451149],
        "sundiscSunsetColor":[0.50196081399918,0.50196081399918,0.50196081399918],
        "ambientSunriseColor":[0.23921570181847,0.15686275064945,0.15686275064945],
        "fogSunriseColor":[0.35294118523598,0.13725490868092,0.13725490868092],
        "ambientNightColor":[0.13908794522285,0.11788634210825,0.11925628036261],
        "fogNightColor":[0.17254902422428,0.054901964962482,0.054901964962482],
        "skySunriseColor":[0.35294118523598,0.13725490868092,0.13725490868092]
      },
      "Foggy":{
        "sunDayColor":[0.21962037682533,0.29703664779663,0.36818897724152],
        "skySunsetColor":[0.47081074118614,0.53650468587875,0.60134601593018],
        "fogSunsetColor":[0.34270742535591,0.42831048369408,0.51132094860077],
        "fogDayColor":[0.48607814311981,0.65710681676865,0.75473684072495],
        "skyNightColor":[0.070588238537312,0.090196080505848,0.10980392992496],
        "cloudTexture":"Data Files\\Textures\\tew\\Watch the Skies\\foggy\\tew_foggy_8.dds",
        "ambientSunsetColor":[0.037203457206488,0.1454494446516,0.23077918589115],
        "skyDayColor":[0.58605700731277,0.68980902433395,0.75425976514816],
        "ambientDayColor":[0.15250065922737,0.21639657020569,0.25486010313034],
        "sunNightColor":[0,0.0003210631548427,0.0033814334310591],
        "sunSunriseColor":[0.4954861998558,0.44230937957764,0.35018336772919],
        "sunSunsetColor":[0.080016784369946,0.22901935875416,0.33435860276222],
        "sundiscSunsetColor":[0.87450987100601,0.87450987100601,0.87450987100601],
        "ambientSunriseColor":[0.18823531270027,0.16862745583057,0.14509804546833],
        "fogSunriseColor":[0.62761372327805,0.59301960468292,0.53118234872818],
        "ambientNightColor":[0.10980392992496,0.1294117718935,0.15294118225574],
        "fogNightColor":[0.074509806931019,0.094117656350136,0.11372549831867],
        "skySunriseColor":[0.66302198171616,0.63651061058044,0.59841102361679]
      },
      "Blizzard":{
        "sunDayColor":[0.63921570777893,0.66274511814117,0.71764707565308],
        "skySunsetColor":[0.42352944612503,0.45098042488098,0.47450983524323],
        "fogSunsetColor":[0.42352944612503,0.45098042488098,0.47450983524323],
        "fogDayColor":[0.47450983524323,0.52156865596771,0.5686274766922],
        "skyNightColor":[0.10588236153126,0.11372549831867,0.12156863510609],
        "cloudTexture":"Data Files\\Textures\\tew\\Watch the Skies\\blizzard\\tew_blizzard_1.dds",
        "ambientSunsetColor":[0.32549020648003,0.30196079611778,0.29411765933037],
        "skyDayColor":[0.47450983524323,0.52156865596771,0.5686274766922],
        "ambientDayColor":[0.3647058904171,0.37647062540054,0.41176474094391],
        "sunNightColor":[0,0,0],
        "sunSunriseColor":[0.44705885648727,0.50196081399918,0.57254904508591],
        "sunSunsetColor":[0.41568630933762,0.44705885648727,0.53333336114883],
        "sundiscSunsetColor":[0.50196081399918,0.50196081399918,0.50196081399918],
        "ambientSunriseColor":[0.32941177487373,0.34509804844856,0.36078432202339],
        "fogSunriseColor":[0.35686275362968,0.38823533058167,0.41568630933762],
        "ambientNightColor":[0.13319529592991,0.16760174930096,0.19717580080032],
        "fogNightColor":[0.082352943718433,0.094117656350136,0.10980392992496],
        "skySunriseColor":[0.35686275362968,0.38823533058167,0.41568630933762]
      },
      "Snow":{
        "sunDayColor":[0.63921570777893,0.66274511814117,0.71764707565308],
        "skySunsetColor":[0.37647062540054,0.45098042488098,0.52549022436142],
        "fogSunsetColor":[0.37647062540054,0.45098042488098,0.52549022436142],
        "fogDayColor":[0.60000002384186,0.61960786581039,0.65098041296005],
        "skyNightColor":[0.064186863601208,0.080973483622074,0.0964250639081],
        "cloudTexture":"Data Files\\Textures\\tew\\Watch the Skies\\snow\\tew_snow_3.dds",
        "ambientSunsetColor":[0.27450981736183,0.3098039329052,0.34117648005486],
        "skyDayColor":[0.60000002384186,0.61960786581039,0.65098041296005],
        "ambientDayColor":[0.3647058904171,0.37647062540054,0.41176474094391],
        "sunNightColor":[0,0,0],
        "sunSunriseColor":[0.55294120311737,0.42745101451874,0.42745101451874],
        "sunSunsetColor":[0.39607846736908,0.47450983524323,0.55294120311737],
        "sundiscSunsetColor":[0.50196081399918,0.50196081399918,0.50196081399918],
        "ambientSunriseColor":[0.36078432202339,0.32941177487373,0.32941177487373],
        "fogSunriseColor":[0.41568630933762,0.35686275362968,0.35686275362968],
        "ambientNightColor":[0.055956102907658,0.091643966734409,0.12595999240875],
        "fogNightColor":[0.09400936961174,0.10939289629459,0.12459093332291],
        "skySunriseColor":[0.41568630933762,0.35686275362968,0.35686275362968]
      },
      "Cloudy":{
        "sunDayColor":[0.92721158266068,0.85404008626938,0.79609370231628],
        "skySunsetColor":[0.43529415130615,0.44705885648727,0.6235294342041],
        "fogSunsetColor":[1,0.60784316062927,0.41568630933762],
        "fogDayColor":[0.96078437566757,0.9215686917305,0.87843143939972],
        "skyNightColor":[0.035294119268656,0.039215687662363,0.04313725605607],
        "cloudTexture":"Data Files\\Textures\\tew\\Watch the Skies\\cloudy\\tew_cloudy_1.dds",
        "ambientSunsetColor":[0.16226330399513,0.19675235450268,0.24029952287674],
        "skyDayColor":[0.4588235616684,0.62745100259781,0.84313732385635],
        "ambientDayColor":[0.15881681442261,0.18830229341984,0.23690547049046],
        "sunNightColor":[0,0,0.0068414774723351],
        "sunSunriseColor":[0.94509810209274,0.69411766529083,0.38823533058167],
        "sunSunsetColor":[0.89824628829956,0.30957221984863,0],
        "sundiscSunsetColor":[1,0.79215693473816,0.70196080207825],
        "ambientSunriseColor":[0.13214787840843,0.16314099729061,0.20957879722118],
        "fogSunriseColor":[0.96577262878418,0.77984017133713,0.55387187004089],
        "ambientNightColor":[0.12549020349979,0.15294118225574,0.21176472306252],
        "fogNightColor":[0.035294119268656,0.039215687662363,0.04313725605607],
        "skySunriseColor":[0.49411767721176,0.61960786581039,0.678431391716]
      },
      "Rain":{
        "sunDayColor":[0.20102991163731,0.18595404922962,0.14265641570091],
        "skySunsetColor":[0.28545963764191,0.34886607527733,0.35759830474854],
        "fogSunsetColor":[0.4127134680748,0.32778054475784,0.32217818498611],
        "fogDayColor":[0.36384445428848,0.43251198530197,0.4648489356041],
        "skyNightColor":[0.081204041838646,0.099845044314861,0.11683562397957],
        "cloudTexture":"Data Files\\Textures\\tew\\Watch the Skies\\rain\\tew_rain_5.dds",
        "ambientSunsetColor":[0.1112614646554,0.14208818972111,0.14223478734493],
        "skyDayColor":[0.40016430616379,0.48057913780212,0.51824933290482],
        "ambientDayColor":[0.12863418459892,0.1455280482769,0.15538981556892],
        "sunNightColor":[0,0,0],
        "sunSunriseColor":[0.11208707094193,0.058020383119583,0.03980765864253],
        "sunSunsetColor":[0.14291286468506,0.12074195593596,0.1089845970273],
        "sundiscSunsetColor":[0.60142254829407,0.36795821785927,0.21291066706181],
        "ambientSunriseColor":[0.16360051929951,0.14029233157635,0.13358156383038],
        "fogSunriseColor":[0.31569689512253,0.28170013427734,0.26246014237404],
        "ambientNightColor":[0.075424358248711,0.08593162894249,0.11160441488028],
        "fogNightColor":[0.077358268201351,0.10032089054585,0.12071197479963],
        "skySunriseColor":[0.25812008976936,0.29440093040466,0.30619725584984]
      },
      "Overcast":{
        "sunDayColor":[0.085917726159096,0.085905246436596,0.085903540253639],
        "skySunsetColor":[0.42352944612503,0.45098042488098,0.47450983524323],
        "fogSunsetColor":[0.42352944612503,0.45098042488098,0.47450983524323],
        "fogDayColor":[0.43598797917366,0.4724947810173,0.50718730688095],
        "skyNightColor":[0.074509806931019,0.086274512112141,0.098039224743843],
        "cloudTexture":"Data Files\\Textures\\tew\\Watch the Skies\\overcast\\tew_overcast_2.dds",
        "ambientSunsetColor":[0.17545230686665,0.15454845130444,0.14752757549286],
        "skyDayColor":[0.47542795538902,0.51733082532883,0.55699807405472],
        "ambientDayColor":[0.1451920568943,0.15631240606308,0.18687431514263],
        "sunNightColor":[0,0,0],
        "sunSunriseColor":[0.34117648005486,0.49019610881805,0.63921570777893],
        "sunSunsetColor":[0.10570139437914,0.045593611896038,0.0076475199311972],
        "sundiscSunsetColor":[0.50196081399918,0.50196081399918,0.50196081399918],
        "ambientSunriseColor":[0.32941177487373,0.34509804844856,0.36078432202339],
        "fogSunriseColor":[0.35686275362968,0.38823533058167,0.41568630933762],
        "ambientNightColor":[0.086294338107109,0.097323007881641,0.11797527968884],
        "fogNightColor":[0.074509806931019,0.086274512112141,0.098039224743843],
        "skySunriseColor":[0.35686275362968,0.38823533058167,0.41568630933762]
      },
      "Thunderstorm":{
        "sunDayColor":[0.54117649793625,0.56470590829849,0.60784316062927],
        "skySunsetColor":[0.13725490868092,0.14117647707462,0.15294118225574],
        "fogSunsetColor":[0.20419792830944,0.21969915926456,0.26089152693748],
        "fogDayColor":[0.38039219379425,0.4078431725502,0.45098042488098],
        "skyNightColor":[0.074509806931019,0.078431375324726,0.086274512112141],
        "cloudTexture":"Data Files\\Textures\\tew\\Watch the Skies\\thunder\\tew_thunder_1.dds",
        "ambientSunsetColor":[0.13165095448494,0.13165640830994,0.13165716826916],
        "skyDayColor":[0.38039219379425,0.4078431725502,0.45098042488098],
        "ambientDayColor":[0.35294118523598,0.35294118523598,0.35294118523598],
        "sunNightColor":[0,0,0],
        "sunSunriseColor":[0.35686275362968,0.38823533058167,0.47843140363693],
        "sunSunsetColor":[0,0,0.006479465868324],
        "sundiscSunsetColor":[0.50196081399918,0.50196081399918,0.50196081399918],
        "ambientSunriseColor":[0.21176472306252,0.21176472306252,0.21176472306252],
        "fogSunriseColor":[0.27450981736183,0.29019609093666,0.33333334326744],
        "ambientNightColor":[0.10517771542072,0.11253328621387,0.12334340065718],
        "fogNightColor":[0.074509806931019,0.078431375324726,0.086274512112141],
        "skySunriseColor":[0.13725490868092,0.14117647707462,0.15294118225574]
      },
      "inscatter":[0.33899363478309,0.46428195747218,0.56173119369083],
      "Clear":{
        "sunDayColor":[0.84224450588226,0.83100444078445,0.77785503864288],
        "skySunsetColor":[0.21960785984993,0.34901961684227,0.50588238239288],
        "fogSunsetColor":[1,0.74117648601532,0.61568629741669],
        "fogDayColor":[0.72258764505386,0.80422419309616,0.91192454099655],
        "skyNightColor":[0.035294119268656,0.039215687662363,0.04313725605607],
        "cloudTexture":"Data Files\\Textures\\tew\\Watch the Skies\\clear\\tew_clear_12.dds",
        "ambientSunsetColor":[0.26666668057442,0.29411765933037,0.37647062540054],
        "skyDayColor":[0.37254902720451,0.52941179275513,0.79607850313187],
        "ambientDayColor":[0.29858899116516,0.31086161732674,0.38179984688759],
        "sunNightColor":[0,0,0.011251660063863],
        "sunSunriseColor":[0.94901967048645,0.6235294342041,0.46666669845581],
        "sunSunsetColor":[1,0.44705885648727,0.3098039329052],
        "sundiscSunsetColor":[1,0.74117648601532,0.61568629741669],
        "ambientSunriseColor":[0.1843137294054,0.258823543787,0.37647062540054],
        "fogSunriseColor":[1,0.74117648601532,0.61568629741669],
        "ambientNightColor":[0.12549020349979,0.13725490868092,0.16470588743687],
        "fogNightColor":[0.035294119268656,0.039215687662363,0.04313725605607],
        "skySunriseColor":[0.4588235616684,0.55294120311737,0.64313727617264]
      }
    },
    "CC_Firemoth":{
      "outscatter":[0.005,0.005,0.005],
      "Blizzard":{
        "sunDayColor":[0,0,0],
        "skySunsetColor":[0,0.15999999642372,0.11999999731779],
        "fogSunsetColor":[0,0.17499999701977,0.15500000119209],
        "fogDayColor":[0,0.17499999701977,0.15500000119209],
        "skyNightColor":[0,0.15999999642372,0.11999999731779],
        "cloudTexture":"Data Files\\Textures\\tx_sky_clear.tga",
        "ambientSunsetColor":[0.070000000298023,0.17000000178814,0.090000003576279],
        "ambientSunriseColor":[0.070000000298023,0.17000000178814,0.090000003576279],
        "ambientDayColor":[0.070000000298023,0.17000000178814,0.090000003576279],
        "sunNightColor":[0,0,0],
        "ambientNightColor":[0.070000000298023,0.17000000178814,0.090000003576279],
        "sunSunsetColor":[0,0,0],
        "sundiscSunsetColor":[0,0,0],
        "skyDayColor":[0,0.15999999642372,0.11999999731779],
        "fogSunriseColor":[0,0.17499999701977,0.15500000119209],
        "sunSunriseColor":[0,0,0],
        "fogNightColor":[0,0.17499999701977,0.15500000119209],
        "skySunriseColor":[0,0.15999999642372,0.11999999731779]
      },
      "Blight":{
        "sunDayColor":[0,0,0],
        "skySunsetColor":[0,0.15999999642372,0.11999999731779],
        "fogSunsetColor":[0,0.17499999701977,0.15500000119209],
        "fogDayColor":[0,0.17499999701977,0.15500000119209],
        "skyNightColor":[0,0.15999999642372,0.11999999731779],
        "cloudTexture":"Data Files\\Textures\\tx_sky_clear.tga",
        "ambientSunsetColor":[0.070000000298023,0.17000000178814,0.090000003576279],
        "ambientSunriseColor":[0.070000000298023,0.17000000178814,0.090000003576279],
        "ambientDayColor":[0.070000000298023,0.17000000178814,0.090000003576279],
        "sunNightColor":[0,0,0],
        "ambientNightColor":[0.070000000298023,0.17000000178814,0.090000003576279],
        "sunSunsetColor":[0,0,0],
        "sundiscSunsetColor":[0,0,0],
        "skyDayColor":[0,0.15999999642372,0.11999999731779],
        "fogSunriseColor":[0,0.17499999701977,0.15500000119209],
        "sunSunriseColor":[0,0,0],
        "fogNightColor":[0,0.17499999701977,0.15500000119209],
        "skySunriseColor":[0,0.15999999642372,0.11999999731779]
      },
      "Foggy":{
        "sunDayColor":[0,0,0],
        "skySunsetColor":[0,0.15999999642372,0.11999999731779],
        "fogSunsetColor":[0,0.17499999701977,0.15500000119209],
        "fogDayColor":[0,0.17499999701977,0.15500000119209],
        "skyNightColor":[0,0.15999999642372,0.11999999731779],
        "cloudTexture":"Data Files\\Textures\\tx_sky_clear.tga",
        "ambientSunsetColor":[0.070000000298023,0.17000000178814,0.090000003576279],
        "ambientSunriseColor":[0.070000000298023,0.17000000178814,0.090000003576279],
        "ambientDayColor":[0.070000000298023,0.17000000178814,0.090000003576279],
        "sunNightColor":[0,0,0],
        "ambientNightColor":[0.070000000298023,0.17000000178814,0.090000003576279],
        "sunSunsetColor":[0,0,0],
        "sundiscSunsetColor":[0,0,0],
        "skyDayColor":[0,0.15999999642372,0.11999999731779],
        "fogSunriseColor":[0,0.17499999701977,0.15500000119209],
        "sunSunriseColor":[0,0,0],
        "fogNightColor":[0,0.17499999701977,0.15500000119209],
        "skySunriseColor":[0,0.15999999642372,0.11999999731779]
      },
      "Ashstorm":{
        "sunDayColor":[0,0,0],
        "skySunsetColor":[0,0.15999999642372,0.11999999731779],
        "fogSunsetColor":[0,0.17499999701977,0.15500000119209],
        "fogDayColor":[0,0.17499999701977,0.15500000119209],
        "skyNightColor":[0,0.15999999642372,0.11999999731779],
        "cloudTexture":"Data Files\\Textures\\tx_sky_clear.tga",
        "ambientSunsetColor":[0.070000000298023,0.17000000178814,0.090000003576279],
        "ambientSunriseColor":[0.070000000298023,0.17000000178814,0.090000003576279],
        "ambientDayColor":[0.070000000298023,0.17000000178814,0.090000003576279],
        "sunNightColor":[0,0,0],
        "ambientNightColor":[0.070000000298023,0.17000000178814,0.090000003576279],
        "sunSunsetColor":[0,0,0],
        "sundiscSunsetColor":[0,0,0],
        "skyDayColor":[0,0.15999999642372,0.11999999731779],
        "fogSunriseColor":[0,0.17499999701977,0.15500000119209],
        "sunSunriseColor":[0,0,0],
        "fogNightColor":[0,0.17499999701977,0.15500000119209],
        "skySunriseColor":[0,0.15999999642372,0.11999999731779]
      },
      "Snow":{
        "sunDayColor":[0,0,0],
        "skySunsetColor":[0,0.15999999642372,0.11999999731779],
        "fogSunsetColor":[0,0.17499999701977,0.15500000119209],
        "fogDayColor":[0,0.17499999701977,0.15500000119209],
        "skyNightColor":[0,0.15999999642372,0.11999999731779],
        "cloudTexture":"Data Files\\Textures\\tx_sky_clear.tga",
        "ambientSunsetColor":[0.070000000298023,0.17000000178814,0.090000003576279],
        "ambientSunriseColor":[0.070000000298023,0.17000000178814,0.090000003576279],
        "ambientDayColor":[0.070000000298023,0.17000000178814,0.090000003576279],
        "sunNightColor":[0,0,0],
        "ambientNightColor":[0.070000000298023,0.17000000178814,0.090000003576279],
        "sunSunsetColor":[0,0,0],
        "sundiscSunsetColor":[0,0,0],
        "skyDayColor":[0,0.15999999642372,0.11999999731779],
        "fogSunriseColor":[0,0.17499999701977,0.15500000119209],
        "sunSunriseColor":[0,0,0],
        "fogNightColor":[0,0.17499999701977,0.15500000119209],
        "skySunriseColor":[0,0.15999999642372,0.11999999731779]
      },
      "Cloudy":{
        "sunDayColor":[0,0,0],
        "skySunsetColor":[0,0.15999999642372,0.11999999731779],
        "fogSunsetColor":[0,0.17499999701977,0.15500000119209],
        "fogDayColor":[0,0.17499999701977,0.15500000119209],
        "skyNightColor":[0,0.15999999642372,0.11999999731779],
        "cloudTexture":"Data Files\\Textures\\tx_sky_clear.tga",
        "ambientSunsetColor":[0.070000000298023,0.17000000178814,0.090000003576279],
        "ambientSunriseColor":[0.070000000298023,0.17000000178814,0.090000003576279],
        "ambientDayColor":[0.070000000298023,0.17000000178814,0.090000003576279],
        "sunNightColor":[0,0,0],
        "ambientNightColor":[0.070000000298023,0.17000000178814,0.090000003576279],
        "sunSunsetColor":[0,0,0],
        "sundiscSunsetColor":[0,0,0],
        "skyDayColor":[0,0.15999999642372,0.11999999731779],
        "fogSunriseColor":[0,0.17499999701977,0.15500000119209],
        "sunSunriseColor":[0,0,0],
        "fogNightColor":[0,0.17499999701977,0.15500000119209],
        "skySunriseColor":[0,0.15999999642372,0.11999999731779]
      },
      "Rain":{
        "sunDayColor":[0,0,0],
        "skySunsetColor":[0,0.15999999642372,0.11999999731779],
        "fogSunsetColor":[0,0.17499999701977,0.15500000119209],
        "fogDayColor":[0,0.17499999701977,0.15500000119209],
        "skyNightColor":[0,0.15999999642372,0.11999999731779],
        "cloudTexture":"Data Files\\Textures\\tx_sky_clear.tga",
        "ambientSunsetColor":[0.070000000298023,0.17000000178814,0.090000003576279],
        "ambientSunriseColor":[0.070000000298023,0.17000000178814,0.090000003576279],
        "ambientDayColor":[0.070000000298023,0.17000000178814,0.090000003576279],
        "sunNightColor":[0,0,0],
        "ambientNightColor":[0.070000000298023,0.17000000178814,0.090000003576279],
        "sunSunsetColor":[0,0,0],
        "sundiscSunsetColor":[0,0,0],
        "skyDayColor":[0,0.15999999642372,0.11999999731779],
        "fogSunriseColor":[0,0.17499999701977,0.15500000119209],
        "sunSunriseColor":[0,0,0],
        "fogNightColor":[0,0.17499999701977,0.15500000119209],
        "skySunriseColor":[0,0.15999999642372,0.11999999731779]
      },
      "Overcast":{
        "sunDayColor":[0,0,0],
        "skySunsetColor":[0,0.15999999642372,0.11999999731779],
        "fogSunsetColor":[0,0.17499999701977,0.15500000119209],
        "fogDayColor":[0,0.17499999701977,0.15500000119209],
        "skyNightColor":[0,0.15999999642372,0.11999999731779],
        "cloudTexture":"Data Files\\Textures\\tx_sky_clear.tga",
        "ambientSunsetColor":[0.070000000298023,0.17000000178814,0.090000003576279],
        "ambientSunriseColor":[0.070000000298023,0.17000000178814,0.090000003576279],
        "ambientDayColor":[0.070000000298023,0.17000000178814,0.090000003576279],
        "sunNightColor":[0,0,0],
        "ambientNightColor":[0.070000000298023,0.17000000178814,0.090000003576279],
        "sunSunsetColor":[0,0,0],
        "sundiscSunsetColor":[0,0,0],
        "skyDayColor":[0,0.15999999642372,0.11999999731779],
        "fogSunriseColor":[0,0.17499999701977,0.15500000119209],
        "sunSunriseColor":[0,0,0],
        "fogNightColor":[0,0.17499999701977,0.15500000119209],
        "skySunriseColor":[0,0.15999999642372,0.11999999731779]
      },
      "Thunderstorm":{
        "sunDayColor":[0,0,0],
        "skySunsetColor":[0,0.15999999642372,0.11999999731779],
        "fogSunsetColor":[0,0.17499999701977,0.15500000119209],
        "fogDayColor":[0,0.17499999701977,0.15500000119209],
        "skyNightColor":[0,0.15999999642372,0.11999999731779],
        "cloudTexture":"Data Files\\Textures\\tx_sky_clear.tga",
        "ambientSunsetColor":[0.070000000298023,0.17000000178814,0.090000003576279],
        "ambientSunriseColor":[0.070000000298023,0.17000000178814,0.090000003576279],
        "ambientDayColor":[0.070000000298023,0.17000000178814,0.090000003576279],
        "sunNightColor":[0,0,0],
        "ambientNightColor":[0.070000000298023,0.17000000178814,0.090000003576279],
        "sunSunsetColor":[0,0,0],
        "sundiscSunsetColor":[0,0,0],
        "skyDayColor":[0,0.15999999642372,0.11999999731779],
        "fogSunriseColor":[0,0.17499999701977,0.15500000119209],
        "sunSunriseColor":[0,0,0],
        "fogNightColor":[0,0.17499999701977,0.15500000119209],
        "skySunriseColor":[0,0.15999999642372,0.11999999731779]
      },
      "inscatter":[0.005,0.005,0.005],
      "Clear":{
        "sunDayColor":[0,0,0],
        "skySunsetColor":[0,0.15999999642372,0.11999999731779],
        "fogSunsetColor":[0,0.17499999701977,0.15500000119209],
        "fogDayColor":[0,0.17499999701977,0.15500000119209],
        "skyNightColor":[0,0.15999999642372,0.11999999731779],
        "cloudTexture":"Data Files\\Textures\\tx_sky_clear.tga",
        "ambientSunsetColor":[0.070000000298023,0.17000000178814,0.090000003576279],
        "ambientSunriseColor":[0.070000000298023,0.17000000178814,0.090000003576279],
        "ambientDayColor":[0.070000000298023,0.17000000178814,0.090000003576279],
        "sunNightColor":[0,0,0],
        "ambientNightColor":[0.070000000298023,0.17000000178814,0.090000003576279],
        "sunSunsetColor":[0,0,0],
        "sundiscSunsetColor":[0,0,0],
        "skyDayColor":[0,0.15999999642372,0.11999999731779],
        "fogSunriseColor":[0,0.17499999701977,0.15500000119209],
        "sunSunriseColor":[0,0,0],
        "fogNightColor":[0,0.17499999701977,0.15500000119209],
        "skySunriseColor":[0,0.15999999642372,0.11999999731779]
      }
    },
    "default":{
      "outscatter":[0.07,0.36,0.76],
      "Ashstorm":{
        "sunDayColor":[0.89411771297455,0.54509806632996,0.44705885648727],
        "skySunsetColor":[0.41568630933762,0.21568629145622,0.15686275064945],
        "fogSunsetColor":[0.41568630933762,0.21568629145622,0.15686275064945],
        "fogDayColor":[0.48627454042435,0.28627452254295,0.22745099663734],
        "skyNightColor":[0.078431375324726,0.082352943718433,0.086274512112141],
        "fogSunriseColor":[0.35686275362968,0.21960785984993,0.20000001788139],
        "ambientSunsetColor":[0.18823531270027,0.15294118225574,0.13725490868092],
        "skyDayColor":[0.48627454042435,0.28627452254295,0.22745099663734],
        "ambientDayColor":[0.29411765933037,0.19215688109398,0.16078431904316],
        "sunNightColor":[0.21176472306252,0.258823543787,0.29019609093666],
        "ambientNightColor":[0.14117647707462,0.16470588743687,0.19215688109398],
        "sunSunsetColor":[0.72549021244049,0.33725491166115,0.22352942824364],
        "sundiscSunsetColor":[0.50196081399918,0.50196081399918,0.50196081399918],
        "cloudTexture":"Data Files\\Textures\\tew\\Watch the Skies\\ash\\tew_ash_3.dds",
        "sunSunriseColor":[0.72156864404678,0.35686275362968,0.27843138575554],
        "ambientSunriseColor":[0.21176472306252,0.16470588743687,0.14509804546833],
        "fogNightColor":[0.078431375324726,0.082352943718433,0.086274512112141],
        "skySunriseColor":[0.35686275362968,0.21960785984993,0.20000001788139]
      },
      "Blight":{
        "sunDayColor":[0.87843143939972,0.32941177487373,0.32941177487373],
        "skySunsetColor":[0.36078432202339,0.1294117718935,0.1294117718935],
        "fogSunsetColor":[0.36078432202339,0.1294117718935,0.1294117718935],
        "fogDayColor":[0.50196081399918,0.074509806931019,0.074509806931019],
        "skyNightColor":[0.17254902422428,0.054901964962482,0.054901964962482],
        "fogSunriseColor":[0.35294118523598,0.13725490868092,0.13725490868092],
        "ambientSunsetColor":[0.23921570181847,0.15686275064945,0.15686275064945],
        "skyDayColor":[0.35294118523598,0.13725490868092,0.13725490868092],
        "ambientDayColor":[0.3098039329052,0.21176472306252,0.21176472306252],
        "sunNightColor":[0.23921570181847,0.35686275362968,0.56078433990479],
        "ambientNightColor":[0.21960785984993,0.22745099663734,0.24313727021217],
        "sunSunsetColor":[0.70588237047195,0.30588236451149,0.30588236451149],
        "sundiscSunsetColor":[0.50196081399918,0.50196081399918,0.50196081399918],
        "cloudTexture":"Data Files\\Textures\\tew\\Watch the Skies\\blight\\tew_blight_4.dds",
        "sunSunriseColor":[0.70588237047195,0.30588236451149,0.30588236451149],
        "ambientSunriseColor":[0.23921570181847,0.15686275064945,0.15686275064945],
        "fogNightColor":[0.17254902422428,0.054901964962482,0.054901964962482],
        "skySunriseColor":[0.35294118523598,0.13725490868092,0.13725490868092]
      },
      "Foggy":{
        "sunDayColor":[0.43529415130615,0.5137255191803,0.59215688705444],
        "skySunsetColor":[0.55686277151108,0.6235294342041,0.69019609689713],
        "fogSunsetColor":[0.44313728809357,0.52941179275513,0.61568629741669],
        "fogDayColor":[0.58823531866074,0.73333334922791,0.81960791349411],
        "skyNightColor":[0.070588238537312,0.090196080505848,0.10980392992496],
        "fogSunriseColor":[0.678431391716,0.64313727617264,0.58039218187332],
        "ambientSunsetColor":[0.11372549831867,0.20784315466881,0.29803922772408],
        "skyDayColor":[0.72156864404678,0.82745105028152,0.89411771297455],
        "ambientDayColor":[0.36078432202339,0.42745101451874,0.47058826684952],
        "sunNightColor":[0.31764706969261,0.39215689897537,0.46666669845581],
        "ambientNightColor":[0.10980392992496,0.1294117718935,0.15294118225574],
        "sunSunsetColor":[0.49019610881805,0.61568629741669,0.74117648601532],
        "sundiscSunsetColor":[0.87450987100601,0.87450987100601,0.87450987100601],
        "cloudTexture":"Data Files\\Textures\\tew\\Watch the Skies\\foggy\\tew_foggy_5.dds",
        "sunSunriseColor":[0.69411766529083,0.63529413938522,0.53725492954254],
        "ambientSunriseColor":[0.18823531270027,0.16862745583057,0.14509804546833],
        "fogNightColor":[0.074509806931019,0.094117656350136,0.11372549831867],
        "skySunriseColor":[0.77254909276962,0.74509805440903,0.70588237047195]
      },
      "inscatter":[0.25,0.38,0.48],
      "Snow":{
        "sunDayColor":[0.63921570777893,0.66274511814117,0.71764707565308],
        "skySunsetColor":[0.37647062540054,0.45098042488098,0.52549022436142],
        "fogSunsetColor":[0.37647062540054,0.45098042488098,0.52549022436142],
        "fogDayColor":[0.60000002384186,0.61960786581039,0.65098041296005],
        "skyNightColor":[0.12156863510609,0.13725490868092,0.15294118225574],
        "fogSunriseColor":[0.41568630933762,0.35686275362968,0.35686275362968],
        "ambientSunsetColor":[0.27450981736183,0.3098039329052,0.34117648005486],
        "skyDayColor":[0.60000002384186,0.61960786581039,0.65098041296005],
        "ambientDayColor":[0.3647058904171,0.37647062540054,0.41176474094391],
        "sunNightColor":[0.21568629145622,0.258823543787,0.30196079611778],
        "ambientNightColor":[0.19215688109398,0.22745099663734,0.26666668057442],
        "sunSunsetColor":[0.39607846736908,0.47450983524323,0.55294120311737],
        "sundiscSunsetColor":[0.50196081399918,0.50196081399918,0.50196081399918],
        "cloudTexture":"Data Files\\Textures\\tew\\Watch the Skies\\snow\\tew_snow_4.dds",
        "sunSunriseColor":[0.55294120311737,0.42745101451874,0.42745101451874],
        "ambientSunriseColor":[0.36078432202339,0.32941177487373,0.32941177487373],
        "fogNightColor":[0.12156863510609,0.13725490868092,0.15294118225574],
        "skySunriseColor":[0.41568630933762,0.35686275362968,0.35686275362968]
      },
      "Cloudy":{
        "sunDayColor":[1,0.92549026012421,0.8666667342186],
        "skySunsetColor":[0.43529415130615,0.44705885648727,0.6235294342041],
        "fogSunsetColor":[1,0.60784316062927,0.41568630933762],
        "fogDayColor":[0.96078437566757,0.9215686917305,0.87843143939972],
        "skyNightColor":[0.035294119268656,0.039215687662363,0.04313725605607],
        "fogSunriseColor":[1,0.8117647767067,0.58431375026703],
        "ambientSunsetColor":[0.27843138575554,0.3137255012989,0.36078432202339],
        "skyDayColor":[0.4588235616684,0.62745100259781,0.84313732385635],
        "ambientDayColor":[0.53725492954254,0.5686274766922,0.62745100259781],
        "sunNightColor":[0.30196079611778,0.35686275362968,0.48627454042435],
        "ambientNightColor":[0.12549020349979,0.15294118225574,0.21176472306252],
        "sunSunsetColor":[1,0.34901961684227,0],
        "sundiscSunsetColor":[1,0.79215693473816,0.70196080207825],
        "cloudTexture":"Data Files\\Textures\\tew\\Watch the Skies\\cloudy\\tew_cloudy_3.dds",
        "sunSunriseColor":[0.94509810209274,0.69411766529083,0.38823533058167],
        "ambientSunriseColor":[0.258823543787,0.29019609093666,0.34117648005486],
        "fogNightColor":[0.035294119268656,0.039215687662363,0.04313725605607],
        "skySunriseColor":[0.49411767721176,0.61960786581039,0.678431391716]
      },
      "Rain":{
        "sunDayColor":[0.58431375026703,0.61568629741669,0.66666668653488],
        "skySunsetColor":[0.28627452254295,0.28627452254295,0.28627452254295],
        "fogSunsetColor":[0.28627452254295,0.28627452254295,0.28627452254295],
        "fogDayColor":[0.45490199327469,0.47058826684952,0.47843140363693],
        "skyNightColor":[0.094117656350136,0.098039224743843,0.10196079313755],
        "fogSunriseColor":[0.27843138575554,0.29019609093666,0.29411765933037],
        "ambientSunsetColor":[0.34509804844856,0.38039219379425,0.38039219379425],
        "skyDayColor":[0.45490199327469,0.47058826684952,0.47843140363693],
        "ambientDayColor":[0.41176474094391,0.43137258291245,0.44313728809357],
        "sunNightColor":[0.19607844948769,0.24313727021217,0.39607846736908],
        "ambientNightColor":[0.19607844948769,0.21568629145622,0.26274511218071],
        "sunSunsetColor":[0.47058826684952,0.49411767721176,0.5137255191803],
        "sundiscSunsetColor":[0.50196081399918,0.50196081399918,0.50196081399918],
        "cloudTexture":"Data Files\\Textures\\tew\\Watch the Skies\\rain\\tew_rain_6.dds",
        "sunSunriseColor":[0.5137255191803,0.47843140363693,0.47058826684952],
        "ambientSunriseColor":[0.38039219379425,0.35294118523598,0.34509804844856],
        "fogNightColor":[0.094117656350136,0.098039224743843,0.10196079313755],
        "skySunriseColor":[0.27843138575554,0.29019609093666,0.29411765933037]
      },
      "Blizzard":{
        "sunDayColor":[0.63921570777893,0.66274511814117,0.71764707565308],
        "skySunsetColor":[0.42352944612503,0.45098042488098,0.47450983524323],
        "fogSunsetColor":[0.42352944612503,0.45098042488098,0.47450983524323],
        "fogDayColor":[0.47450983524323,0.52156865596771,0.5686274766922],
        "skyNightColor":[0.10588236153126,0.11372549831867,0.12156863510609],
        "fogSunriseColor":[0.35686275362968,0.38823533058167,0.41568630933762],
        "ambientSunsetColor":[0.32549020648003,0.30196079611778,0.29411765933037],
        "skyDayColor":[0.47450983524323,0.52156865596771,0.5686274766922],
        "ambientDayColor":[0.3647058904171,0.37647062540054,0.41176474094391],
        "sunNightColor":[0.22352942824364,0.258823543787,0.29019609093666],
        "ambientNightColor":[0.20784315466881,0.24313727021217,0.27450981736183],
        "sunSunsetColor":[0.41568630933762,0.44705885648727,0.53333336114883],
        "sundiscSunsetColor":[0.50196081399918,0.50196081399918,0.50196081399918],
        "cloudTexture":"Data Files\\Textures\\tew\\Watch the Skies\\blizzard\\tew_blizzard_4.dds",
        "sunSunriseColor":[0.44705885648727,0.50196081399918,0.57254904508591],
        "ambientSunriseColor":[0.32941177487373,0.34509804844856,0.36078432202339],
        "fogNightColor":[0.082352943718433,0.094117656350136,0.10980392992496],
        "skySunriseColor":[0.35686275362968,0.38823533058167,0.41568630933762]
      },
      "Thunderstorm":{
        "sunDayColor":[0.54117649793625,0.56470590829849,0.60784316062927],
        "skySunsetColor":[0.13725490868092,0.14117647707462,0.15294118225574],
        "fogSunsetColor":[0.27450981736183,0.29019609093666,0.33333334326744],
        "fogDayColor":[0.38039219379425,0.4078431725502,0.45098042488098],
        "skyNightColor":[0.074509806931019,0.078431375324726,0.086274512112141],
        "fogSunriseColor":[0.27450981736183,0.29019609093666,0.33333334326744],
        "ambientSunsetColor":[0.21176472306252,0.21176472306252,0.21176472306252],
        "skyDayColor":[0.38039219379425,0.4078431725502,0.45098042488098],
        "ambientDayColor":[0.35294118523598,0.35294118523598,0.35294118523598],
        "sunNightColor":[0.21568629145622,0.29803922772408,0.43137258291245],
        "ambientNightColor":[0.19215688109398,0.20000001788139,0.21176472306252],
        "sunSunsetColor":[0.37647062540054,0.39607846736908,0.4588235616684],
        "sundiscSunsetColor":[0.50196081399918,0.50196081399918,0.50196081399918],
        "cloudTexture":"Data Files\\Textures\\tew\\Watch the Skies\\thunder\\tew_thunder_5.dds",
        "sunSunriseColor":[0.35686275362968,0.38823533058167,0.47843140363693],
        "ambientSunriseColor":[0.21176472306252,0.21176472306252,0.21176472306252],
        "fogNightColor":[0.074509806931019,0.078431375324726,0.086274512112141],
        "skySunriseColor":[0.13725490868092,0.14117647707462,0.15294118225574]
      },
      "Overcast":{
        "sunDayColor":[0.63921570777893,0.66274511814117,0.71764707565308],
        "skySunsetColor":[0.42352944612503,0.45098042488098,0.47450983524323],
        "fogSunsetColor":[0.42352944612503,0.45098042488098,0.47450983524323],
        "fogDayColor":[0.56078433990479,0.57254904508591,0.58431375026703],
        "skyNightColor":[0.074509806931019,0.086274512112141,0.098039224743843],
        "fogSunriseColor":[0.35686275362968,0.38823533058167,0.41568630933762],
        "ambientSunsetColor":[0.32549020648003,0.30196079611778,0.29411765933037],
        "skyDayColor":[0.56078433990479,0.57254904508591,0.58431375026703],
        "ambientDayColor":[0.3647058904171,0.37647062540054,0.41176474094391],
        "sunNightColor":[0.12549020349979,0.21176472306252,0.39215689897537],
        "ambientNightColor":[0.22352942824364,0.23529413342476,0.258823543787],
        "sunSunsetColor":[0.33333334326744,0.40392160415649,0.61568629741669],
        "sundiscSunsetColor":[0.50196081399918,0.50196081399918,0.50196081399918],
        "cloudTexture":"Data Files\\Textures\\tew\\Watch the Skies\\overcast\\tew_overcast_5.dds",
        "sunSunriseColor":[0.34117648005486,0.49019610881805,0.63921570777893],
        "ambientSunriseColor":[0.32941177487373,0.34509804844856,0.36078432202339],
        "fogNightColor":[0.074509806931019,0.086274512112141,0.098039224743843],
        "skySunriseColor":[0.35686275362968,0.38823533058167,0.41568630933762]
      },
      "Clear":{
        "sunDayColor":[1,0.98823535442352,0.93333339691162],
        "skySunsetColor":[0.21960785984993,0.34901961684227,0.50588238239288],
        "fogSunsetColor":[1,0.74117648601532,0.61568629741669],
        "fogDayColor":[0.80784320831299,0.89019614458084,1],
        "skyNightColor":[0.035294119268656,0.039215687662363,0.04313725605607],
        "fogSunriseColor":[1,0.74117648601532,0.61568629741669],
        "ambientSunsetColor":[0.26666668057442,0.29411765933037,0.37647062540054],
        "skyDayColor":[0.37254902720451,0.52941179275513,0.79607850313187],
        "ambientDayColor":[0.53725492954254,0.54901963472366,0.62745100259781],
        "sunNightColor":[0.23137256503105,0.38039219379425,0.69019609689713],
        "ambientNightColor":[0.12549020349979,0.13725490868092,0.16470588743687],
        "sunSunsetColor":[1,0.44705885648727,0.3098039329052],
        "sundiscSunsetColor":[1,0.74117648601532,0.61568629741669],
        "cloudTexture":"Data Files\\Textures\\tew\\Watch the Skies\\clear\\tew_clear_16.dds",
        "sunSunriseColor":[0.94901967048645,0.6235294342041,0.46666669845581],
        "ambientSunriseColor":[0.1843137294054,0.258823543787,0.37647062540054],
        "fogNightColor":[0.035294119268656,0.039215687662363,0.04313725605607],
        "skySunriseColor":[0.4588235616684,0.55294120311737,0.64313727617264]
      }
    }
  },
  "messageOnRegionChange":false,
  "keybind":{
    "keyCode":62,
    "isShiftDown":true,
    "class":"TableVariable",
    "isAltDown":false,
    "isControlDown":false
  },
  "disableSkyTextureChanges":true
}